verisptab/__init__.py
verisptab/generate.py
verisptab-0.1.0.dist-info/METADATA
verisptab-0.1.0.dist-info/WHEEL
verisptab-0.1.0.dist-info/licenses/LICENSE
verisptab-0.1.0.dist-info/RECORD
