Metadata-Version: 2.1
Name: verisptab
Version: 0.1.0
Summary: Privacy preserving tables!
Project-URL: Homepage, https://veris.ai
Author-email: Aditya Rai <team@veris.ai>
License-File: LICENSE
Classifier: License :: OSI Approved :: MIT License
Classifier: Operating System :: OS Independent
Classifier: Programming Language :: Python :: 3
Requires-Python: >=3.7
Requires-Dist: pandas
Requires-Dist: requests
